OrensteinLabKit/Configuration.txt
OrensteinLabKit/__init__.py
OrensteinLabKit/Instrument/__init__.py
OrensteinLabKit/Instrument/Lakeshore/Lakeshore336.py
OrensteinLabKit/Instrument/Lakeshore/__init__.py
OrensteinLabKit/Instrument/OptiCool/OptiCool_Control.py
OrensteinLabKit/Instrument/OptiCool/__init__.py
OrensteinLabKit/Instrument/OptiCool/parse_inputs.py
OrensteinLabKit/Instrument/OptiCool/qd_socket_client.py
OrensteinLabKit/Instrument/OptiCool/qd_socket_server.py
OrensteinLabKit/Instrument/OptiCool/qdcommandparser.py
OrensteinLabKit/Instrument/OptiCool/qdinstrument.py
OrensteinLabKit/Instrument/OptiCool/qdscafolding.py
OrensteinLabKit/Measurement/__init__.py
OrensteinLabKit/Measurement/Yue/Measurement.py
OrensteinLabKit/Measurement/Yue/__init__.py
OrensteinLabKit/Operation/ESP301.py
OrensteinLabKit/Operation/__init__.py
OrensteinLabKit/Operation/Attocube/__init__.py
OrensteinLabKit/Operation/Attocube/v2/Attocube_v2.py
OrensteinLabKit/Operation/Attocube/v2/__init__.py
OrensteinLabKit/Operation/Attocube/v4/Attocube_v4.py
OrensteinLabKit/Operation/Attocube/v4/__init__.py
OrensteinLabKit-0.0.6.dist-info/LICENSE.txt
OrensteinLabKit-0.0.6.dist-info/METADATA
OrensteinLabKit-0.0.6.dist-info/WHEEL
OrensteinLabKit-0.0.6.dist-info/top_level.txt
OrensteinLabKit-0.0.6.dist-info/RECORD
