Metadata-Version: 2.1
Name: OrensteinLabKit
Version: 0.0.6
Summary: A package to control all the measurements in Orenstein lab
Author: Yue Sun
Author-email: yue.sun@berkeley.edu
Keywords: Experiment Control
Classifier: Development Status :: 4 - Beta
Classifier: License :: OSI Approved :: MIT License
Classifier: Programming Language :: Python :: 3.8
Requires-Python: >=3.8, <4
License-File: LICENSE.txt
Requires-Dist: lakeshore
Requires-Dist: zhinst
Requires-Dist: InstrumentKit
Requires-Dist: pyanc350
